fastapi_gen/__init__.py
fastapi_gen/__main__.py
fastapi_gen/core/__init__.py
fastapi_gen/core/_create_model.py
fastapi_gen/core/action.py
fastapi_gen/core/base.py
fastapi_gen/core/migration.py
fastapi_gen/core/project_template/app_name.jinja2
fastapi_gen/core/project_template/project_name/__init__.jinja2
fastapi_gen/core/project_template/project_name/api/__init__.jinja2
fastapi_gen/core/project_template/project_name/api/item.jinja2
fastapi_gen/core/project_template/project_name/models/__init__.jinja2
fastapi_gen/core/project_template/project_name/schema/__init__.jinja2
fastapi_gen/core/project_template/project_name/schema/item.jinja2
fastapi_gen/exceptions.py
fastapi_gen/gen.py
fastapi_gen/utils/__init__.py
fastapi_gen/utils/enum.py
fastapi_gen/utils/stdout_patch.py
fastapi_gene-0.0.8.dist-info/METADATA
fastapi_gene-0.0.8.dist-info/WHEEL
fastapi_gene-0.0.8.dist-info/entry_points.txt
fastapi_gene-0.0.8.dist-info/licenses/LICENSE
fastapi_gene-0.0.8.dist-info/RECORD
