Metadata-Version: 2.1
Name: fastapi-gene
Version: 0.0.8
Summary: Create and Run migration for fastapi project
Author-Email: bhuwan pandey <bhuwanpandey@gmail.com>
License: MIT
Classifier: Intended Audience :: Information Technology
Classifier: Intended Audience :: System Administrators
Classifier: Operating System :: OS Independent
Classifier: Programming Language :: Python :: 3
Classifier: Programming Language :: Python
Classifier: Topic :: Software Development :: Libraries :: Application Frameworks
Classifier: Topic :: Software Development :: Libraries :: Python Modules
Classifier: Topic :: Software Development :: Libraries
Classifier: Topic :: Software Development
Classifier: Typing :: Typed
Classifier: Development Status :: 4 - Beta
Classifier: Framework :: FastAPI
Classifier: Intended Audience :: Developers
Classifier: License :: OSI Approved :: MIT License
Classifier: Programming Language :: Python :: 3 :: Only
Classifier: Programming Language :: Python :: 3.8
Classifier: Programming Language :: Python :: 3.9
Classifier: Programming Language :: Python :: 3.10
Classifier: Programming Language :: Python :: 3.11
Classifier: Programming Language :: Python :: 3.12
Requires-Python: >=3.8
Requires-Dist: typer>=0.12.3
Requires-Dist: rich-toolkit>=0.11.1
Requires-Dist: jinja2>=3.1.6
Requires-Dist: httpx>=0.28.1
Requires-Dist: alembic>=1.14.1
Requires-Dist: click<=8.1.8,>=8.0.0
